phantoms/__init__.py
phantoms-0.0.1.dist-info/LICENSE
phantoms-0.0.1.dist-info/WHEEL
phantoms-0.0.1.dist-info/METADATA
phantoms-0.0.1.dist-info/RECORD
